{
    "clubs": [
      {
        "name": "Bayern Munich",
        "total_goals_scored": 70,
        "wins": 23,
        "losses": 2,
        "draws": 5,
        "cups_won": 4,
        "cards_received": {
          "yellow": 40,
          "red": 2
        }
      },
      {
        "name": "Borussia Dortmund",
        "total_goals_scored": 65,
        "wins": 18,
        "losses": 6,
        "draws": 5,
        "cups_won": 2,
        "cards_received": {
          "yellow": 50,
          "red": 1
        }
      },
      {
        "name": "RB Leipzig",
        "total_goals_scored": 60,
        "wins": 17,
        "losses": 7,
        "draws": 6,
        "cups_won": 1,
        "cards_received": {
          "yellow": 45,
          "red": 3
        }
      },
      {
        "name": "Bayer Leverkusen",
        "total_goals_scored": 58,
        "wins": 16,
        "losses": 8,
        "draws": 6,
        "cups_won": 1,
        "cards_received": {
          "yellow": 42,
          "red": 2
        }
      },
      {
        "name": "Schalke 04",
        "total_goals_scored": 28,
        "wins": 4,
        "losses": 22,
        "draws": 4,
        "cups_won": 0,
        "cards_received": {
          "yellow": 60,
          "red": 4
        }
      },
      {
        "name": "VfL Wolfsburg",
        "total_goals_scored": 50,
        "wins": 13,
        "losses": 10,
        "draws": 7,
        "cups_won": 1,
        "cards_received": {
          "yellow": 35,
          "red": 1
        }
      },
      {
        "name": "Eintracht Frankfurt",
        "total_goals_scored": 52,
        "wins": 15,
        "losses": 9,
        "draws": 6,
        "cups_won": 0,
        "cards_received": {
          "yellow": 48,
          "red": 2
        }
      },
      {
        "name": "Werder Bremen",
        "total_goals_scored": 42,
        "wins": 9,
        "losses": 14,
        "draws": 5,
        "cups_won": 1,
        "cards_received": {
          "yellow": 40,
          "red": 1
        }
      },
      {
        "name": "Hoffenheim",
        "total_goals_scored": 48,
        "wins": 10,
        "losses": 14,
        "draws": 4,
        "cups_won": 0,
        "cards_received": {
          "yellow": 38,
          "red": 0
        }
      },
      {
        "name": "Hertha BSC",
        "total_goals_scored": 36,
        "wins": 6,
        "losses": 18,
        "draws": 6,
        "cups_won": 0,
        "cards_received": {
          "yellow": 45,
          "red": 3
        }
      }
    ]
  }